expressionable/__init__.py
expressionable/expressionable.py
expressionable/errors/__init__.py
expressionable/errors/columnnotfounderror.py
expressionable/errors/sizeexceedederror.py
expressionable/files/__init__.py
expressionable/files/arffile.py
expressionable/files/csvfile.py
expressionable/files/eafile.py
expressionable/files/excelfile.py
expressionable/files/fwffile.py
expressionable/files/gctfile.py
expressionable/files/gctxfile.py
expressionable/files/geofile.py
expressionable/files/hdf5file.py
expressionable/files/htmlfile.py
expressionable/files/jsonfile.py
expressionable/files/jupyternotebookfile.py
expressionable/files/kallisto_est_counts_file.py
expressionable/files/kallisto_tpm_file.py
expressionable/files/msgpackfile.py
expressionable/files/parquetfile.py
expressionable/files/pdffile.py
expressionable/files/picklefile.py
expressionable/files/rmarkdownfile.py
expressionable/files/salmon_num_reads_file.py
expressionable/files/salmon_tpm_file.py
expressionable/files/sqlitefile.py
expressionable/files/star_reads_file.py
expressionable/files/statafile.py
expressionable/files/tsvfile.py
expressionable/utils/__init__.py
expressionable/utils/columninfo.py
expressionable/utils/continuousquery.py
expressionable/utils/convertarff.py
expressionable/utils/convertgct.py
expressionable/utils/convertgctx.py
expressionable/utils/createparquet.py
expressionable/utils/discretequery.py
expressionable/utils/filetypeenum.py
expressionable/utils/kallisto.py
expressionable/utils/mergetoparquet.py
expressionable/utils/operatorenum.py
expressionable/utils/salmon.py
expressionable/utils/star.py
expressionable-1.2.dist-info/LICENSE
expressionable-1.2.dist-info/METADATA
expressionable-1.2.dist-info/WHEEL
expressionable-1.2.dist-info/top_level.txt
expressionable-1.2.dist-info/RECORD
