Metadata-Version: 2.1
Name: expressionable
Version: 1.2
Summary: A tool for managing large datasets
Home-page: https://github.com/srp33/ExpressionAble
Author: Piccolo Lab
Author-email: stephen_piccolo@byu.edu
License: MIT
Platform: UNKNOWN
Requires-Dist: pandas
Requires-Dist: pyarrow
Requires-Dist: matplotlib
Requires-Dist: numpy
Requires-Dist: sqlalchemy
Requires-Dist: xlsxwriter
Requires-Dist: tables
Requires-Dist: xlrd
Requires-Dist: nbformat
Requires-Dist: cmapPy
Requires-Dist: tabula-py
